brazil_types/__init__.py
brazil_types/types.py
brazil_types-0.0.3.dist-info/DESCRIPTION.rst
brazil_types-0.0.3.dist-info/METADATA
brazil_types-0.0.3.dist-info/RECORD
brazil_types-0.0.3.dist-info/WHEEL
brazil_types-0.0.3.dist-info/metadata.json
brazil_types-0.0.3.dist-info/top_level.txt
