Metadata-Version: 2.0
Name: brazil-types
Version: 0.0.3
Summary: Biblioteca com os tipos de dados usados no Brasil.
Home-page: https://github.com/gestaolivre/brazil-types
Author: Sergio Garcia
Author-email: contato@gestaolivre.org
License: MIT
Download-URL: https://github.com/gestaolivre/brazil-types/releases
Keywords: brazil types receita federal
Platform: UNKNOWN
Classifier: Development Status :: 3 - Alpha
Classifier: Intended Audience :: Developers
Classifier: License :: OSI Approved :: MIT License
Classifier: Programming Language :: Python :: 2
Classifier: Programming Language :: Python :: 2.7
Classifier: Programming Language :: Python :: 3
Classifier: Programming Language :: Python :: 3.4
Classifier: Programming Language :: Python :: 3.5
Requires-Dist: six
